{"graphSize": 100, "interval": 1000, "line-fmt": {"current": "#73d216", "available": {"red-solid": "r-", "green-solid": "g-", "yellow-solid": "y-", "blue-solid": "b-", "cyan-solid": "c-", "magenta-solid": "m-", "black-solid": "k-", "white-solid": "w-", "red-dashed": "r--", "green-dashed": "g--", "yellow-dashed": "y--", "blue-dashed": "b--", "cyan-dashed": "c--", "magenta-dashed": "m--", "black-dashed": "k--", "white-dashed": "w--", "red-dash-dotted": "r-.", "green-dash-dotted": "g-.", "yellow-dash-dotted": "y-.", "blue-dash-dotted": "b-.", "cyan-dash-dotted": "c-.", "magenta-dash-dotted": "m-.", "black-dash-dotted": "k-.", "white-dash-dotted": "w-.", "red-dotted": "r:", "green-dotted": "g:", "yellow-dotted": "y:", "blue-dotted": "b:", "cyan-dotted": "c:", "magenta-dotted": "m:", "back-dotted": "k:", "white-dotted": "w:"}}, "facecolor": {"current": "#24256b"}, "tabsConfig": {"main": "Processing", "net": "Monitor", "disk": "Monitor", "sensors": "Temperatures"}, "useLogger": true, "dbName": "hydrogenous", "dbTable": "logs", "serverAddress": "localhost", "serverPort": 3306, "serverUser": "carl"}